amazon_product_review_scraper/__init__.py
amazon_product_review_scraper/amazon_product_review_scraper.py
amazon_product_review_scraper-0.9.dist-info/LICENSE
amazon_product_review_scraper-0.9.dist-info/METADATA
amazon_product_review_scraper-0.9.dist-info/WHEEL
amazon_product_review_scraper-0.9.dist-info/top_level.txt
amazon_product_review_scraper-0.9.dist-info/RECORD
