Metadata-Version: 2.1
Name: amazon_product_review_scraper
Version: 0.9
Summary: Python package to scrape product review data from amazon
Home-page: https://github.com/SinghalHarsh/amazon-product-review-scraper
Author: Harsh Singhal
Author-email: harshsinghal726@gmail.com
License: MIT
Keywords: Scraper,Amazon,Reviews
Platform: UNKNOWN
Requires-Python: >=3.6
